{"scoring":"В этой задаче 10 тестов, каждый оценивается независимо в 10 баллов.","notes":"","legend":"Комната характеризуется тремя целыми числами: длиной, шириной и высотой, заданными в миллиметрах. Комната считается хорошей, если выполнены следующие условия: отношение меньшей из длины и ширины к высоте хотя бы $2$, а также отношение большей из длины и ширины к меньшей не превосходит $2$.\r\n\r\nПо заданным размерам комнаты определите, является ли она хорошей.","authorLogin":"andrewzta","language":"russian","timeLimit":1000,"output":"Если комната является хорошей, выведите <<\\texttt{good}>>, иначе выведите <<\\texttt{bad}>>.","inputFile":"stdin","outputFile":"stdout","input":"На вход подаётся три целых числа: $w$, $l$ и $h$ --- длина, ширина и высота комнаты, каждое на отдельной строке ($1000 \\le w, l, h \\le 10\\,000$).","authorName":"Andrew Stankevich","sampleTests":[{"output":"bad\r\n","input":"4000\r\n6000\r\n3000\r\n","inputFile":"example.01","outputFile":"example.01.a"},{"output":"good\r\n","input":"4600\r\n8600\r\n1600\r\n","inputFile":"example.02","outputFile":"example.02.a"}],"name":"Комната","interaction":null,"memoryLimit":268435456,"tutorial":""}